spike_encoding/__init__.py
spike_encoding/base_converter.py
spike_encoding/bens_spiker_algorithm.py
spike_encoding/bin_encoder.py
spike_encoding/dataset_utils/__init__.py
spike_encoding/dataset_utils/download_shd.py
spike_encoding/dataset_utils/process_shd.py
spike_encoding/datasets.py
spike_encoding/delta_modulation_converter.py
spike_encoding/encoder_common.py
spike_encoding/gymnasium_bounds_finder.py
spike_encoding/gymnasium_encoder.py
spike_encoding/lif_based_encoding.py
spike_encoding/pulse_width_modulation.py
spike_encoding/rate_step_forward_converter.py
spike_encoding/step_forward_converter.py
spike_encoding-0.1.6.dist-info/WHEEL
spike_encoding-0.1.6.dist-info/METADATA
spike_encoding-0.1.6.dist-info/RECORD
