Metadata-Version: 2.3
Name: spike-encoding
Version: 0.1.6
Summary: A spike-encoding repository for converting conventional data to spiking data. Includes trainable encoding methods and PyTorch compatibility, as well as integration of some common datasets.
Author: Alexandru Vasilache, Jona Scholz
Author-email: Alexandru Vasilache <vasilache@fzi.de>, Jona Scholz <jona.scholz@kit.edu>
Requires-Dist: colorama>=0.4.6
Requires-Dist: gymnasium[classic-control]>=1.2.0
Requires-Dist: h5py>=3.14.0
Requires-Dist: joblib>=1.5.2
Requires-Dist: optuna>=4.5.0
Requires-Dist: pandas>=2.3.2
Requires-Dist: scikit-learn>=1.7.1
Requires-Dist: torch>=2.8.0
Requires-Dist: torchmetrics>=1.8.2
Requires-Dist: tqdm>=4.67.1
Requires-Python: >=3.10
